{"list":[{"url":"https://www.pixiv.net/en/artworks/95269499","views":2542,"views_day":32766,"likes":338,"likes_day":4356,"date":"2022-01-03T09:12:14.000Z"},{"url":"https://www.pixiv.net/en/artworks/95270239","views":1177,"views_day":21032,"likes":169,"likes_day":3020,"date":"2022-01-03T09:43:22.000Z"},{"url":"https://www.pixiv.net/en/artworks/95058723","views":82199,"views_day":10955,"likes":8625,"likes_day":1149,"date":"2021-12-26T23:00:05.000Z"},{"url":"https://www.pixiv.net/en/artworks/94924910","views":109285,"views_day":8514,"likes":9385,"likes_day":731,"date":"2021-12-21T15:01:47.000Z"},{"url":"https://www.pixiv.net/en/artworks/94615347","views":116239,"views_day":4176,"likes":15430,"likes_day":554,"date":"2021-12-06T15:04:01.000Z"},{"url":"https://www.pixiv.net/en/artworks/95229763","views":5957,"views_day":3504,"likes":459,"likes_day":270,"date":"2022-01-01T18:16:16.000Z"},{"url":"https://www.pixiv.net/en/artworks/95090563","views":19830,"views_day":3309,"likes":1888,"likes_day":315,"date":"2021-12-28T11:14:40.000Z"},{"url":"https://www.pixiv.net/en/artworks/95170762","views":9775,"views_day":3273,"likes":1905,"likes_day":638,"date":"2021-12-31T11:24:28.000Z"},{"url":"https://www.pixiv.net/en/artworks/94905866","views":44822,"views_day":3239,"likes":3484,"likes_day":251,"date":"2021-12-20T15:00:12.000Z"},{"url":"https://www.pixiv.net/en/artworks/95229789","views":4647,"views_day":2736,"likes":385,"likes_day":226,"date":"2022-01-01T18:18:47.000Z"}]}